relplot/__init__.py
relplot/config.py
relplot/diagrams.py
relplot/estimators.py
relplot/kernels.py
relplot/metrics.py
relplot-1.0.3.dist-info/licenses/LICENSE
relplot-1.0.3.dist-info/METADATA
relplot-1.0.3.dist-info/WHEEL
relplot-1.0.3.dist-info/top_level.txt
relplot-1.0.3.dist-info/RECORD
