Metadata-Version: 2.4
Name: relplot
Version: 1.0.3
Summary: Compute and plot reliability diagrams based on calibration distance.
Author: Preetum Nakkiran, Jarosław Błasiok
License: Copyright (C) 2023 Apple Inc. All Rights Reserved.
Project-URL: Homepage, https://github.com/apple/ml-calibration
Classifier: Programming Language :: Python :: 3
Classifier: Operating System :: OS Independent
Requires-Python: >=3.7
License-File: LICENSE
Requires-Dist: numpy
Requires-Dist: scipy
Requires-Dist: pandas
Requires-Dist: matplotlib
Requires-Dist: scikit-learn
Requires-Dist: seaborn
Requires-Dist: deprecation
Dynamic: license-file
